biothings_mcp/__init__.py
biothings_mcp/biothings_api.py
biothings_mcp/download_api.py
biothings_mcp/server.py
mseep_biothings_mcp-0.1.4.dist-info/licenses/LICENSE
mseep_biothings_mcp-0.1.4.dist-info/METADATA
mseep_biothings_mcp-0.1.4.dist-info/WHEEL
mseep_biothings_mcp-0.1.4.dist-info/entry_points.txt
mseep_biothings_mcp-0.1.4.dist-info/top_level.txt
mseep_biothings_mcp-0.1.4.dist-info/RECORD
