Metadata-Version: 2.4
Name: mseep-biothings-mcp
Version: 0.1.4
Summary: MCP for Biothings
Author-email: mseep <support@skydeck.ai>
Requires-Python: >=3.10
License-File: LICENSE
Requires-Dist: biopython>=1.85
Requires-Dist: biothings-typed-client>=0.0.7
Requires-Dist: eliot>=1.17.5
Requires-Dist: pycomfort>=0.0.18
Requires-Dist: fastmcp>=2.10.2
Requires-Dist: aiosqlite>=0.21.0
Requires-Dist: sqlite-utils>=3.38
Requires-Dist: huggingface-hub>=0.33.2
Requires-Dist: typer>=0.16.0
Dynamic: license-file
